TESTXMZAPI/KVS.py
TESTXMZAPI/__init__.py
TESTXMZAPI/HWNLP/__init__.py
TESTXMZAPI/HWNLP/auth_config.py
TESTXMZAPI/HWNLP/mt_service.py
TESTXMZAPI/HWNLP/nlg_service.py
TESTXMZAPI/HWNLP/nlpf_service.py
TESTXMZAPI/HWNLP/nlu_service.py
TESTXMZAPI-1.5.0.dist-info/LICENSE
TESTXMZAPI-1.5.0.dist-info/METADATA
TESTXMZAPI-1.5.0.dist-info/WHEEL
TESTXMZAPI-1.5.0.dist-info/top_level.txt
TESTXMZAPI-1.5.0.dist-info/RECORD
