Metadata-Version: 2.1
Name: TESTXMZAPI
Version: 1.5.0
Summary: 米粥SDK
Home-page: https://github.com/xiaomizhoubaobei/XMZAPI
Author: 祁筱欣
Author-email: mzapi@x.mizhoubaobei.top
Classifier: Programming Language :: Python :: 3
Classifier: License :: OSI Approved :: MIT License
Classifier: Operating System :: OS Independent
License-File: LICENSE
Requires-Dist: huaweicloudsdkcore
Requires-Dist: huaweicloudsdknlp
